latloncalc/__init__.py
latloncalc/latlon.py
latloncalc-1.5.6.dist-info/LICENSE.txt
latloncalc-1.5.6.dist-info/METADATA
latloncalc-1.5.6.dist-info/WHEEL
latloncalc-1.5.6.dist-info/top_level.txt
latloncalc-1.5.6.dist-info/RECORD
