Metadata-Version: 2.1
Name: latloncalc
Version: 1.5.6
Summary: Geographical calculations with longitudes/latitudes coordinates
Home-page: https://github.com/eelcovv/latloncalc
Author: Eelco van Vliet
Author-email: eelcovv@gmail.com
License: MIT
Project-URL: Documentation, http://latloncalc.readthedocs.io/
Project-URL: Source, https://github.com/eelcovv/latloncalc
Project-URL: Changelog, https://latloncalc.readthedocs.io/en/latest/changelog.html
Project-URL: Download, https://pypi.org/project/latloncalc/#files
Platform: any
Classifier: Development Status :: 4 - Beta
Classifier: Programming Language :: Python
License-File: LICENSE.txt
Requires-Dist: pyproj
Requires-Dist: numpy
Requires-Dist: importlib-metadata ; python_version < "3.8"
Provides-Extra: testing
Requires-Dist: setuptools ; extra == 'testing'
Requires-Dist: pytest ; extra == 'testing'
Requires-Dist: pytest-cov ; extra == 'testing'
